xindata_package_test/__init__.py
xindata_package_test/pkg_1.py
xindata_package_test/pkg_2.py
xindata_package_test/test1/__init__.py
xindata_package_test/test1/pt_test1_1.py
xindata_package_test/test1/pt_test1_2.py
xindata_package_test/test2/__init__.py
xindata_package_test/test2/pt_test2_1.py
xindata_package_test/test2/pt_test2_2.py
xindata_package_test-0.0.1.dist-info/LICENSE.txt
xindata_package_test-0.0.1.dist-info/METADATA
xindata_package_test-0.0.1.dist-info/WHEEL
xindata_package_test-0.0.1.dist-info/top_level.txt
xindata_package_test-0.0.1.dist-info/RECORD
