Metadata-Version: 2.1
Name: xindata-package-test
Version: 0.0.1
Summary: A test package
Author: Xin_data
Author-email: jaxmin.lee@outlook.com
License: UNKNOWN
Platform: UNKNOWN
Classifier: Programming Language :: Python :: 3
Classifier: License :: OSI Approved :: MIT License
Requires-Python: >=3.6
License-File: LICENSE.txt
